CHANGELOG.md
LICENSE.txt
MANIFEST.in
README.md
setup.py
dplabtools/__init__.py
dplabtools/_version.py
dplabtools.egg-info/PKG-INFO
dplabtools.egg-info/SOURCES.txt
dplabtools.egg-info/dependency_links.txt
dplabtools.egg-info/requires.txt
dplabtools.egg-info/top_level.txt
dplabtools/common/__init__.py
dplabtools/common/common.py
dplabtools/config/__init__.py
dplabtools/config/common.py
dplabtools/config/slides.py
dplabtools/slides/__init__.py
dplabtools/slides/annotations/__init__.py
dplabtools/slides/annotations/mappers/__init__.py
dplabtools/slides/annotations/mappers/asap.py
dplabtools/slides/annotations/mappers/base.py
dplabtools/slides/annotations/mappers/sedeen.py
dplabtools/slides/annotations/mappers/utils.py
dplabtools/slides/annotations/parsers/__init__.py
dplabtools/slides/annotations/parsers/asap.py
dplabtools/slides/annotations/parsers/base.py
dplabtools/slides/annotations/parsers/sedeen.py
dplabtools/slides/annotations/readers/__init__.py
dplabtools/slides/annotations/readers/asap.py
dplabtools/slides/annotations/readers/base.py
dplabtools/slides/annotations/readers/qupath.py
dplabtools/slides/annotations/readers/sedeen.py
dplabtools/slides/annotations/validators/__init__.py
dplabtools/slides/annotations/validators/asap.py
dplabtools/slides/annotations/validators/base.py
dplabtools/slides/annotations/validators/sedeen.py
dplabtools/slides/libs/__init__.py
dplabtools/slides/libs/abstractlib.py
dplabtools/slides/libs/baseslide.py
dplabtools/slides/libs/genericslide.py
dplabtools/slides/libs/libcalls.py
dplabtools/slides/libs/libopenslide.py
dplabtools/slides/libs/libpillow.py
dplabtools/slides/libs/libtiffopenslide.py
dplabtools/slides/libs/libtiffslide.py
dplabtools/slides/libs/mppfunctions.py
dplabtools/slides/patches/__init__.py
dplabtools/slides/patches/extractors/__init__.py
dplabtools/slides/patches/extractors/base.py
dplabtools/slides/patches/extractors/finalclasses.py
dplabtools/slides/patches/extractors/mixins.py
dplabtools/slides/patches/extractors/pools.py
dplabtools/slides/patches/locations/__init__.py
dplabtools/slides/patches/locations/base.py
dplabtools/slides/patches/locations/finalclasses.py
