Metadata-Version: 2.1
Name: dplabtools
Version: 0.0.3
Summary: Digital Pathology Lab Tools
Home-page: https://github.com/martellab-sri/dplabtools
Author: Sunnybrook Research Institute
License: Apache 2.0
Download-URL: https://github.com/martellab-sri/dplabtools
Platform: UNKNOWN
License-File: LICENSE.txt
